scrape_api.py
scrape_api-0.0.1.dist-info/License
scrape_api-0.0.1.dist-info/METADATA
scrape_api-0.0.1.dist-info/WHEEL
scrape_api-0.0.1.dist-info/top_level.txt
scrape_api-0.0.1.dist-info/RECORD
