Metadata-Version: 2.1
Name: scrape-api
Version: 0.0.1
Summary: A Python wrapper for Reddit scraping API. 
Home-page: UNKNOWN
Author: Ali Haider
Author-email: alinisarhaider@gmail.com
License: UNKNOWN
Platform: UNKNOWN
Classifier: Programming Language :: Python :: 3
Classifier: License :: OSI Approved :: MIT License
Classifier: Operating System :: OS Independent
Requires-Python: >=3.6
Requires-Dist: requests
